<?xml version="1.0" encoding="utf-8"?>
<TableObject xmlns:xsd="http://www.w3.org/2001/XMLSchema" xmlns:xsi="http://www.w3.org/2001/XMLSchema-instance">
  <Name>CONTRACT</Name>
  <ID>tbl_CONTRACT</ID>
  <Columns>
    <Column name="CUSTOMER_ID" id="tblCol_87a958c31bea48718b9eed77047bcace" index="0" datatype="Integer" />
    <Column name="CONTRACT_ID" id="tblCol_c693acd01c924613b020f1f1d3e28e6e" index="1" datatype="Integer" mandatory="true" />
    <Column name="CONTRACT_REF_ID" id="tblCol_f23674024bb74f7c8f123ace4af41bde" index="2" datatype="Integer" />
    <Column name="ASSOCIATED_LINE" id="tblCol_dab4ce901c6d4cf996bad4f738193e5f" index="3" datatype="Text" />
    <Column name="CONTRACT_DESCRIPTION" id="tblCol_4e258a4567df4c3f9cd4aeb5ee1da2e9" index="4" datatype="Text" />
    <Column name="FROM_DATE" id="tblCol_678475a3fb844e2eb6d6fdaad0d6438a" index="5" datatype="Text" />
    <Column name="TO_DATE" id="tblCol_b4a9bce2cfdd446b9c12c09eb231a548" index="6" datatype="Text" />
    <Column name="ASSOCIATED_LINE_FMT" id="tblCol_561c9dfc5bf044e99335636993e3b55b" index="7" datatype="Text" />
  </Columns>
  <IndexesList />
  <EnrichmentList />
  <LazyDataUpdate syncMethod="Inherited" performEvery="1.00:00:00">
    <TruncateBeforeSync>true</TruncateBeforeSync>
  </LazyDataUpdate>
</TableObject>